luna/__init__.py
luna/lunaClient.py
luna_client-0.1.0.dist-info/METADATA
luna_client-0.1.0.dist-info/WHEEL
luna_client-0.1.0.dist-info/top_level.txt
luna_client-0.1.0.dist-info/RECORD
